tap_dbt/__init__.py
tap_dbt/client.py
tap_dbt/streams.py
tap_dbt/tap.py
tap_dbt/schemas/__init__.py
tap_dbt/schemas/openapi_v2.yaml
tap_dbt/schemas/openapi_v3.yaml
tap_dbt-0.17.0.dist-info/METADATA
tap_dbt-0.17.0.dist-info/WHEEL
tap_dbt-0.17.0.dist-info/entry_points.txt
tap_dbt-0.17.0.dist-info/licenses/LICENSE
tap_dbt-0.17.0.dist-info/RECORD
