Metadata-Version: 2.4
Name: tap-dbt
Version: 0.17.0
Summary: Singer tap for dbt, built with the Singer SDK.
Project-URL: Documentation, https://github.com/MeltanoLabs/tap-dbt/blob/main/README.md
Project-URL: Homepage, https://github.com/MeltanoLabs/tap-dbt
Project-URL: Repository, https://github.com/MeltanoLabs/tap-dbt
Author-email: Edgar Ramírez Mondragón <edgarrm358@sample.com>
Maintainer-email: Edgar Ramírez Mondragón <edgarrm358@sample.com>
License-Expression: Apache-2.0
License-File: LICENSE
Keywords: dbt,elt,singer-sdk,singer.io
Classifier: Programming Language :: Python :: 3 :: Only
Classifier: Programming Language :: Python :: 3.10
Classifier: Programming Language :: Python :: 3.11
Classifier: Programming Language :: Python :: 3.12
Classifier: Programming Language :: Python :: 3.13
Classifier: Programming Language :: Python :: 3.14
Requires-Python: >=3.10
Requires-Dist: backports-datetime-fromisoformat~=2.0.1; python_full_version < '3.11'
Requires-Dist: pyyaml~=6.0
Requires-Dist: singer-sdk~=0.52.0
Requires-Dist: typing-extensions>=4.14.1
